oneNueron/__init__.py
oneNueron/perceptron.py
oneNueron_pypi_rashi_12-0.0.2.dist-info/LICENSE
oneNueron_pypi_rashi_12-0.0.2.dist-info/METADATA
oneNueron_pypi_rashi_12-0.0.2.dist-info/WHEEL
oneNueron_pypi_rashi_12-0.0.2.dist-info/top_level.txt
oneNueron_pypi_rashi_12-0.0.2.dist-info/RECORD
