Metadata-Version: 2.1
Name: oneNueron-pypi-rashi-12
Version: 0.0.2
Summary: It's an implementation of perceptron
Home-page: https://github.com/rashi_12/oneNueron_pypi
Author: rashi_12
Author-email: agarwalrashi54321@gmail.com
License: UNKNOWN
Project-URL: Bug Tracker, https://github.com/rashi_12/oneNueron_pypi/issues
Platform: UNKNOWN
Classifier: Programming Language :: Python :: 3
Classifier: License :: OSI Approved :: MIT License
Classifier: Operating System :: OS Independent
Requires-Python: >=3.6
License-File: LICENSE
Requires-Dist: numpy
Requires-Dist: tqdm
